vpn_chainer/__init__.py
vpn_chainer/vpn_chainer.py
vpn_chainer-1.3.2.dist-info/licenses/LICENSE
vpn_chainer-1.3.2.dist-info/METADATA
vpn_chainer-1.3.2.dist-info/WHEEL
vpn_chainer-1.3.2.dist-info/entry_points.txt
vpn_chainer-1.3.2.dist-info/top_level.txt
vpn_chainer-1.3.2.dist-info/RECORD
