Metadata-Version: 2.4
Name: vpn-chainer
Version: 1.3.2
Summary: A tool to chain multiple WireGuard VPNs and rotate them dynamically via API
Home-page: https://github.com/a904guy/VPN-Chainer
Author: Andy Hawkins
Author-email: Andy Hawkins <andy+vpnchainer@hawkins.app>
Maintainer: Hawkins.Tech Inc
Maintainer-email: "Hawkins.Tech Inc" <projects+vpnchainer@hawkins.tech>
License: MIT
Project-URL: Homepage, https://github.com/a904guy/VPN-Chainer
Project-URL: Repository, https://github.com/a904guy/VPN-Chainer
Project-URL: Issues, https://github.com/a904guy/VPN-Chainer/issues
Project-URL: Documentation, https://github.com/a904guy/VPN-Chainer/blob/main/README.md
Keywords: vpn,wireguard,proxy,networking,security,privacy
Classifier: Programming Language :: Python :: 3
Classifier: Operating System :: POSIX :: Linux
Classifier: Topic :: Internet :: Proxy Servers
Classifier: Topic :: Security
Classifier: Topic :: System :: Networking
Classifier: Development Status :: 4 - Beta
Classifier: Environment :: Console
Classifier: Intended Audience :: System Administrators
Classifier: Intended Audience :: Developers
Requires-Python: >=3.6
License-File: LICENSE
Requires-Dist: Flask>=2.0.0
Requires-Dist: setproctitle>=1.3.0
Requires-Dist: speedtest-cli>=2.1.0
Dynamic: author
Dynamic: home-page
Dynamic: license-file
Dynamic: maintainer
Dynamic: requires-python
